[
    {
        "index": 1,
        "timestamp": 1717532768.1323516,
        "transactions": [],
        "proof": 100,
        "previous_hash": "1"
    },
    {
        "index": 2,
        "timestamp": 1717532780.469907,
        "transactions": [
            {
                "sender": "26db051a39afb8a010249780311d7e47b9ab2b0e3d205267ea7495967b9b94f0",
                "recipient": "26db051a39afb8a010249780311d7e47b9ab2b0e3d205267ea7495967b9b94f0",
                "content": "\u041f\u0440\u0438\u0432\u0435\u0442",
                "timestamp": 1717532780.2444196
            }
        ],
        "proof": 35293,
        "previous_hash": "7dfcc814977ef14745d7b8c10d346093ff08ac2d90ee304c94f8272f1c15e363"
    },
    {
        "index": 3,
        "timestamp": 1717597619.0339327,
        "transactions": [
            {
                "sender": "aaa885ab772673f022a04ebeebfac8de09386598c9675ed4ac310fe853709daa",
                "recipient": "aaa885ab772673f022a04ebeebfac8de09386598c9675ed4ac310fe853709daa",
                "content": "\u043f\u0440\u0438\u0432\u0435\u0442 \u044d\u0442\u043e \u0442\u0435\u0441\u0442",
                "timestamp": 1717597618.9560742
            }
        ],
        "proof": 35089,
        "previous_hash": "9ead3d85111491b3668666a2ef56b75c139805c6ebe193ea6b0f35711a31a124"
    },
    {
        "index": 4,
        "timestamp": 1717597635.2706134,
        "transactions": [
            {
                "sender": "aaa885ab772673f022a04ebeebfac8de09386598c9675ed4ac310fe853709daa",
                "recipient": "bbf3f128dc453c02de062afcecf99a7e3d8b75f8a3c5d0ba6be043f1413037d0",
                "content": "\u041f\u0440\u0438\u0432\u0435\u0442 \u044d\u0442\u043e \u0442\u0435\u0441\u0442",
                "timestamp": 1717597635.0131612
            }
        ],
        "proof": 119678,
        "previous_hash": "eb0e04a3b7b1f77b88035e716eb030ac261a8d9dc337eb2da26a54d2fc60b419"
    },
    {
        "index": 5,
        "timestamp": 1717597646.0676863,
        "transactions": [
            {
                "sender": "bbf3f128dc453c02de062afcecf99a7e3d8b75f8a3c5d0ba6be043f1413037d0",
                "recipient": "model mango lava hockey airport critic quality project area myself talent cause know discover enemy absurd mobile forest twist whisper stuff valley hospital crucial",
                "content": "\u0447\u0442\u043e \u0442\u0443\u0442 \u043d\u043e\u0432\u043e\u0433\u043e ?:",
                "timestamp": 1717597645.7508814
            }
        ],
        "proof": 146502,
        "previous_hash": "9310340647a22cdda0e71c75fb6efde852b4a8069f09a3657281077d763cdad6"
    },
    {
        "index": 6,
        "timestamp": 1717597666.9777348,
        "transactions": [
            {
                "sender": "bbf3f128dc453c02de062afcecf99a7e3d8b75f8a3c5d0ba6be043f1413037d0",
                "recipient": "aaa885ab772673f022a04ebeebfac8de09386598c9675ed4ac310fe853709daa",
                "content": "\u0427\u0442\u043e \u0442\u0443\u0442 \u043d\u043e\u0432\u043e\u0433\u043e ?",
                "timestamp": 1717597666.8823605
            }
        ],
        "proof": 43538,
        "previous_hash": "61ecbee879992ee9cfb3e40a28d3f2b5cc01f7f8d09ed663148711b6eb8673d2"
    },
    {
        "index": 7,
        "timestamp": 1717601085.1459208,
        "transactions": [
            {
                "sender": "317f648fda983a01e1187b2ff22f3ae3c3e81b710c87d4a0bc9acc617afa924a",
                "recipient": "317f648fda983a01e1187b2ff22f3ae3c3e81b710c87d4a0bc9acc617afa924a",
                "content": "\u041f\u0440\u0438\u0432\u0435\u0442",
                "timestamp": 1717601083.8892086
            }
        ],
        "proof": 85724,
        "previous_hash": "86bf938071d6fdd43dfec7f1a125302ad74f83fb092dd783b7587b42eb36f1a5"
    },
    {
        "index": 8,
        "timestamp": 1717601856.0363355,
        "transactions": [
            {
                "sender": "2079745d10675e69d8e095c50c2a796b3b2a175aadfa66ecedfb4b51baa653df",
                "recipient": "2079745d10675e69d8e095c50c2a796b3b2a175aadfa66ecedfb4b51baa653df",
                "content": "Ghbdtn",
                "timestamp": 1717601855.9166574
            }
        ],
        "proof": 51178,
        "previous_hash": "797c140b8459e9c8922b7ae4e414580c52c074c4fffc3f5db9c45e64269eb504"
    }
]